<profile>

<ReportVersion>
<Version>2016.1</Version>
</ReportVersion>

<UserAssignments>
<unit>ns</unit>
<ProductFamily>kintexu</ProductFamily>
<Part>xcku060-ffva1156-2-e</Part>
<TopModelName>krnl_sobel</TopModelName>
<TargetClockPeriod>5.00</TargetClockPeriod>
<ClockUncertainty>1.35</ClockUncertainty>
</UserAssignments>

<PerformanceEstimates>
<PipelineType>none</PipelineType>
<SummaryOfTimingAnalysis>
<unit>ns</unit>
<EstimatedClockPeriod>4.95</EstimatedClockPeriod>
</SummaryOfTimingAnalysis>
<SummaryOfOverallLatency>
<unit>clock cycles</unit>
<Best-caseLatency>undef</Best-caseLatency>
<Average-caseLatency>undef</Average-caseLatency>
<Worst-caseLatency>undef</Worst-caseLatency>
<Interval-min>undef</Interval-min>
<Interval-max>undef</Interval-max>
</SummaryOfOverallLatency>
<SummaryOfLoopLatency>
<Loop1>
<TripCount>4096</TripCount>
<Latency>4096</Latency>
<IterationLatency>1</IterationLatency>
</Loop1>
<Loop2>
<TripCount>undef</TripCount>
<Latency>undef</Latency>
<IterationLatency>
<range>
<min>144</min>
<max>2147484197</max>
</range>
</IterationLatency>
<memcpy.gmem.krnl_sobel.resbuf>
<TripCount>
<range>
<min>0</min>
<max>1073741823</max>
</range>
</TripCount>
<Latency>
<range>
<min>0</min>
<max>2147483648</max>
</range>
</Latency>
<PipelineII>2</PipelineII>
<PipelineDepth>5</PipelineDepth>
</memcpy.gmem.krnl_sobel.resbuf>
</Loop2>
<memcpy.krnl_sobel.rowbuf0.gmem>
<TripCount>
<range>
<min>0</min>
<max>1073741823</max>
</range>
</TripCount>
<Latency>
<range>
<min>0</min>
<max>2147483647</max>
</range>
</Latency>
<PipelineII>2</PipelineII>
<PipelineDepth>4</PipelineDepth>
</memcpy.krnl_sobel.rowbuf0.gmem>
<memcpy.krnl_sobel.rowbuf1.gmem>
<TripCount>
<range>
<min>0</min>
<max>1073741823</max>
</range>
</TripCount>
<Latency>
<range>
<min>0</min>
<max>2147483647</max>
</range>
</Latency>
<PipelineII>2</PipelineII>
<PipelineDepth>4</PipelineDepth>
</memcpy.krnl_sobel.rowbuf1.gmem>
<Loop5>
<TripCount>
<range>
<min>0</min>
<max>2147483646</max>
</range>
</TripCount>
<Latency>undef</Latency>
<IterationLatency>undef</IterationLatency>
<memcpy.krnl_sobel.rowbuf2.gmem>
<TripCount>
<range>
<min>0</min>
<max>1073741823</max>
</range>
</TripCount>
<Latency>
<range>
<min>0</min>
<max>2147483647</max>
</range>
</Latency>
<PipelineII>2</PipelineII>
<PipelineDepth>4</PipelineDepth>
</memcpy.krnl_sobel.rowbuf2.gmem>
<Loop5.2>
<TripCount>
<range>
<min>0</min>
<max>2147483646</max>
</range>
</TripCount>
<Latency>undef</Latency>
<IterationLatency>undef</IterationLatency>
<Loop5.2.1>
<TripCount>undef</TripCount>
<Latency>undef</Latency>
<IterationLatency>1</IterationLatency>
</Loop5.2.1>
<Loop5.2.2>
<TripCount>undef</TripCount>
<Latency>undef</Latency>
<IterationLatency>1</IterationLatency>
</Loop5.2.2>
</Loop5.2>
</Loop5>
<memcpy.krnl_sobel.rowbuf0.gmem>
<TripCount>
<range>
<min>0</min>
<max>1073741823</max>
</range>
</TripCount>
<Latency>
<range>
<min>0</min>
<max>2147483647</max>
</range>
</Latency>
<PipelineII>2</PipelineII>
<PipelineDepth>4</PipelineDepth>
</memcpy.krnl_sobel.rowbuf0.gmem>
<memcpy.krnl_sobel.rowbuf1.gmem>
<TripCount>
<range>
<min>0</min>
<max>1073741823</max>
</range>
</TripCount>
<Latency>
<range>
<min>0</min>
<max>2147483647</max>
</range>
</Latency>
<PipelineII>2</PipelineII>
<PipelineDepth>4</PipelineDepth>
</memcpy.krnl_sobel.rowbuf1.gmem>
<Loop8>
<TripCount>
<range>
<min>0</min>
<max>2147483646</max>
</range>
</TripCount>
<Latency>undef</Latency>
<IterationLatency>undef</IterationLatency>
<memcpy.krnl_sobel.rowbuf2.gmem>
<TripCount>
<range>
<min>0</min>
<max>1073741823</max>
</range>
</TripCount>
<Latency>
<range>
<min>0</min>
<max>2147483647</max>
</range>
</Latency>
<PipelineII>2</PipelineII>
<PipelineDepth>4</PipelineDepth>
</memcpy.krnl_sobel.rowbuf2.gmem>
<Loop8.2>
<TripCount>
<range>
<min>0</min>
<max>2147483646</max>
</range>
</TripCount>
<Latency>undef</Latency>
<IterationLatency>undef</IterationLatency>
<Loop8.2.1>
<TripCount>undef</TripCount>
<Latency>undef</Latency>
<IterationLatency>1</IterationLatency>
</Loop8.2.1>
<Loop8.2.2>
<TripCount>undef</TripCount>
<Latency>undef</Latency>
<IterationLatency>1</IterationLatency>
</Loop8.2.2>
</Loop8.2>
<memcpy.gmem.krnl_sobel.resbuf>
<TripCount>
<range>
<min>0</min>
<max>1073741823</max>
</range>
</TripCount>
<Latency>
<range>
<min>0</min>
<max>2147483648</max>
</range>
</Latency>
<PipelineII>2</PipelineII>
<PipelineDepth>5</PipelineDepth>
</memcpy.gmem.krnl_sobel.resbuf>
</Loop8>
</SummaryOfLoopLatency>
</PerformanceEstimates>

<AreaEstimates>
<Resources>
<BRAM_18K>14</BRAM_18K>
<DSP48E>29</DSP48E>
<FF>44943</FF>
<LUT>108815</LUT>
</Resources>
<AvailableResources>
<BRAM_18K>2160</BRAM_18K>
<DSP48E>2760</DSP48E>
<FF>663360</FF>
<LUT>331680</LUT>
</AvailableResources>
</AreaEstimates>

<InterfaceSummary>
<RtlPorts>
<name>s_axi_control_AWVALID</name>
<Object>control</Object>
<Type>pointer</Type>
<Scope></Scope>
<IOProtocol>s_axi</IOProtocol>
<IOConfig></IOConfig>
<Dir>in</Dir>
<Bits>1</Bits>
<Attribute>unknown</Attribute>
<CType>int</CType>
<HasCtrl>1</HasCtrl>
</RtlPorts>
<RtlPorts>
<name>s_axi_control_AWREADY</name>
<Object>control</Object>
<Type>pointer</Type>
<Scope></Scope>
<IOProtocol>s_axi</IOProtocol>
<IOConfig></IOConfig>
<Dir>out</Dir>
<Bits>1</Bits>
<Attribute>unknown</Attribute>
<CType>int</CType>
<HasCtrl>1</HasCtrl>
</RtlPorts>
<RtlPorts>
<name>s_axi_control_AWADDR</name>
<Object>control</Object>
<Type>pointer</Type>
<Scope></Scope>
<IOProtocol>s_axi</IOProtocol>
<IOConfig></IOConfig>
<Dir>in</Dir>
<Bits>6</Bits>
<Attribute>unknown</Attribute>
<CType>int</CType>
<HasCtrl>1</HasCtrl>
</RtlPorts>
<RtlPorts>
<name>s_axi_control_WVALID</name>
<Object>control</Object>
<Type>pointer</Type>
<Scope></Scope>
<IOProtocol>s_axi</IOProtocol>
<IOConfig></IOConfig>
<Dir>in</Dir>
<Bits>1</Bits>
<Attribute>unknown</Attribute>
<CType>int</CType>
<HasCtrl>1</HasCtrl>
</RtlPorts>
<RtlPorts>
<name>s_axi_control_WREADY</name>
<Object>control</Object>
<Type>pointer</Type>
<Scope></Scope>
<IOProtocol>s_axi</IOProtocol>
<IOConfig></IOConfig>
<Dir>out</Dir>
<Bits>1</Bits>
<Attribute>unknown</Attribute>
<CType>int</CType>
<HasCtrl>1</HasCtrl>
</RtlPorts>
<RtlPorts>
<name>s_axi_control_WDATA</name>
<Object>control</Object>
<Type>pointer</Type>
<Scope></Scope>
<IOProtocol>s_axi</IOProtocol>
<IOConfig></IOConfig>
<Dir>in</Dir>
<Bits>32</Bits>
<Attribute>unknown</Attribute>
<CType>int</CType>
<HasCtrl>1</HasCtrl>
</RtlPorts>
<RtlPorts>
<name>s_axi_control_WSTRB</name>
<Object>control</Object>
<Type>pointer</Type>
<Scope></Scope>
<IOProtocol>s_axi</IOProtocol>
<IOConfig></IOConfig>
<Dir>in</Dir>
<Bits>4</Bits>
<Attribute>unknown</Attribute>
<CType>int</CType>
<HasCtrl>1</HasCtrl>
</RtlPorts>
<RtlPorts>
<name>s_axi_control_ARVALID</name>
<Object>control</Object>
<Type>pointer</Type>
<Scope></Scope>
<IOProtocol>s_axi</IOProtocol>
<IOConfig></IOConfig>
<Dir>in</Dir>
<Bits>1</Bits>
<Attribute>unknown</Attribute>
<CType>int</CType>
<HasCtrl>1</HasCtrl>
</RtlPorts>
<RtlPorts>
<name>s_axi_control_ARREADY</name>
<Object>control</Object>
<Type>pointer</Type>
<Scope></Scope>
<IOProtocol>s_axi</IOProtocol>
<IOConfig></IOConfig>
<Dir>out</Dir>
<Bits>1</Bits>
<Attribute>unknown</Attribute>
<CType>int</CType>
<HasCtrl>1</HasCtrl>
</RtlPorts>
<RtlPorts>
<name>s_axi_control_ARADDR</name>
<Object>control</Object>
<Type>pointer</Type>
<Scope></Scope>
<IOProtocol>s_axi</IOProtocol>
<IOConfig></IOConfig>
<Dir>in</Dir>
<Bits>6</Bits>
<Attribute>unknown</Attribute>
<CType>int</CType>
<HasCtrl>1</HasCtrl>
</RtlPorts>
<RtlPorts>
<name>s_axi_control_RVALID</name>
<Object>control</Object>
<Type>pointer</Type>
<Scope></Scope>
<IOProtocol>s_axi</IOProtocol>
<IOConfig></IOConfig>
<Dir>out</Dir>
<Bits>1</Bits>
<Attribute>unknown</Attribute>
<CType>int</CType>
<HasCtrl>1</HasCtrl>
</RtlPorts>
<RtlPorts>
<name>s_axi_control_RREADY</name>
<Object>control</Object>
<Type>pointer</Type>
<Scope></Scope>
<IOProtocol>s_axi</IOProtocol>
<IOConfig></IOConfig>
<Dir>in</Dir>
<Bits>1</Bits>
<Attribute>unknown</Attribute>
<CType>int</CType>
<HasCtrl>1</HasCtrl>
</RtlPorts>
<RtlPorts>
<name>s_axi_control_RDATA</name>
<Object>control</Object>
<Type>pointer</Type>
<Scope></Scope>
<IOProtocol>s_axi</IOProtocol>
<IOConfig></IOConfig>
<Dir>out</Dir>
<Bits>32</Bits>
<Attribute>unknown</Attribute>
<CType>int</CType>
<HasCtrl>1</HasCtrl>
</RtlPorts>
<RtlPorts>
<name>s_axi_control_RRESP</name>
<Object>control</Object>
<Type>pointer</Type>
<Scope></Scope>
<IOProtocol>s_axi</IOProtocol>
<IOConfig></IOConfig>
<Dir>out</Dir>
<Bits>2</Bits>
<Attribute>unknown</Attribute>
<CType>int</CType>
<HasCtrl>1</HasCtrl>
</RtlPorts>
<RtlPorts>
<name>s_axi_control_BVALID</name>
<Object>control</Object>
<Type>pointer</Type>
<Scope></Scope>
<IOProtocol>s_axi</IOProtocol>
<IOConfig></IOConfig>
<Dir>out</Dir>
<Bits>1</Bits>
<Attribute>unknown</Attribute>
<CType>int</CType>
<HasCtrl>1</HasCtrl>
</RtlPorts>
<RtlPorts>
<name>s_axi_control_BREADY</name>
<Object>control</Object>
<Type>pointer</Type>
<Scope></Scope>
<IOProtocol>s_axi</IOProtocol>
<IOConfig></IOConfig>
<Dir>in</Dir>
<Bits>1</Bits>
<Attribute>unknown</Attribute>
<CType>int</CType>
<HasCtrl>1</HasCtrl>
</RtlPorts>
<RtlPorts>
<name>s_axi_control_BRESP</name>
<Object>control</Object>
<Type>pointer</Type>
<Scope></Scope>
<IOProtocol>s_axi</IOProtocol>
<IOConfig></IOConfig>
<Dir>out</Dir>
<Bits>2</Bits>
<Attribute>unknown</Attribute>
<CType>int</CType>
<HasCtrl>1</HasCtrl>
</RtlPorts>
<RtlPorts>
<name>ap_clk</name>
<Object>krnl_sobel</Object>
<Type>return value</Type>
<Scope></Scope>
<IOProtocol>ap_ctrl_hs</IOProtocol>
<IOConfig></IOConfig>
<Dir>in</Dir>
<Bits>1</Bits>
<Attribute>control</Attribute>
</RtlPorts>
<RtlPorts>
<name>ap_rst_n</name>
<Object>krnl_sobel</Object>
<Type>return value</Type>
<Scope></Scope>
<IOProtocol>ap_ctrl_hs</IOProtocol>
<IOConfig></IOConfig>
<Dir>in</Dir>
<Bits>1</Bits>
<Attribute>control</Attribute>
</RtlPorts>
<RtlPorts>
<name>interrupt</name>
<Object>krnl_sobel</Object>
<Type>return value</Type>
<Scope></Scope>
<IOProtocol>ap_ctrl_hs</IOProtocol>
<IOConfig></IOConfig>
<Dir>out</Dir>
<Bits>1</Bits>
<Attribute>unknown</Attribute>
</RtlPorts>
<RtlPorts>
<name>m_axi_gmem_AWVALID</name>
<Object>gmem</Object>
<Type>pointer</Type>
<Scope></Scope>
<IOProtocol>m_axi</IOProtocol>
<IOConfig></IOConfig>
<Dir>out</Dir>
<Bits>1</Bits>
<Attribute>unknown</Attribute>
<CType>int</CType>
</RtlPorts>
<RtlPorts>
<name>m_axi_gmem_AWREADY</name>
<Object>gmem</Object>
<Type>pointer</Type>
<Scope></Scope>
<IOProtocol>m_axi</IOProtocol>
<IOConfig></IOConfig>
<Dir>in</Dir>
<Bits>1</Bits>
<Attribute>unknown</Attribute>
<CType>int</CType>
</RtlPorts>
<RtlPorts>
<name>m_axi_gmem_AWADDR</name>
<Object>gmem</Object>
<Type>pointer</Type>
<Scope></Scope>
<IOProtocol>m_axi</IOProtocol>
<IOConfig></IOConfig>
<Dir>out</Dir>
<Bits>64</Bits>
<Attribute>unknown</Attribute>
<CType>int</CType>
</RtlPorts>
<RtlPorts>
<name>m_axi_gmem_AWID</name>
<Object>gmem</Object>
<Type>pointer</Type>
<Scope></Scope>
<IOProtocol>m_axi</IOProtocol>
<IOConfig></IOConfig>
<Dir>out</Dir>
<Bits>1</Bits>
<Attribute>unknown</Attribute>
<CType>int</CType>
</RtlPorts>
<RtlPorts>
<name>m_axi_gmem_AWLEN</name>
<Object>gmem</Object>
<Type>pointer</Type>
<Scope></Scope>
<IOProtocol>m_axi</IOProtocol>
<IOConfig></IOConfig>
<Dir>out</Dir>
<Bits>8</Bits>
<Attribute>unknown</Attribute>
<CType>int</CType>
</RtlPorts>
<RtlPorts>
<name>m_axi_gmem_AWSIZE</name>
<Object>gmem</Object>
<Type>pointer</Type>
<Scope></Scope>
<IOProtocol>m_axi</IOProtocol>
<IOConfig></IOConfig>
<Dir>out</Dir>
<Bits>3</Bits>
<Attribute>unknown</Attribute>
<CType>int</CType>
</RtlPorts>
<RtlPorts>
<name>m_axi_gmem_AWBURST</name>
<Object>gmem</Object>
<Type>pointer</Type>
<Scope></Scope>
<IOProtocol>m_axi</IOProtocol>
<IOConfig></IOConfig>
<Dir>out</Dir>
<Bits>2</Bits>
<Attribute>unknown</Attribute>
<CType>int</CType>
</RtlPorts>
<RtlPorts>
<name>m_axi_gmem_AWLOCK</name>
<Object>gmem</Object>
<Type>pointer</Type>
<Scope></Scope>
<IOProtocol>m_axi</IOProtocol>
<IOConfig></IOConfig>
<Dir>out</Dir>
<Bits>2</Bits>
<Attribute>unknown</Attribute>
<CType>int</CType>
</RtlPorts>
<RtlPorts>
<name>m_axi_gmem_AWCACHE</name>
<Object>gmem</Object>
<Type>pointer</Type>
<Scope></Scope>
<IOProtocol>m_axi</IOProtocol>
<IOConfig></IOConfig>
<Dir>out</Dir>
<Bits>4</Bits>
<Attribute>unknown</Attribute>
<CType>int</CType>
</RtlPorts>
<RtlPorts>
<name>m_axi_gmem_AWPROT</name>
<Object>gmem</Object>
<Type>pointer</Type>
<Scope></Scope>
<IOProtocol>m_axi</IOProtocol>
<IOConfig></IOConfig>
<Dir>out</Dir>
<Bits>3</Bits>
<Attribute>unknown</Attribute>
<CType>int</CType>
</RtlPorts>
<RtlPorts>
<name>m_axi_gmem_AWQOS</name>
<Object>gmem</Object>
<Type>pointer</Type>
<Scope></Scope>
<IOProtocol>m_axi</IOProtocol>
<IOConfig></IOConfig>
<Dir>out</Dir>
<Bits>4</Bits>
<Attribute>unknown</Attribute>
<CType>int</CType>
</RtlPorts>
<RtlPorts>
<name>m_axi_gmem_AWREGION</name>
<Object>gmem</Object>
<Type>pointer</Type>
<Scope></Scope>
<IOProtocol>m_axi</IOProtocol>
<IOConfig></IOConfig>
<Dir>out</Dir>
<Bits>4</Bits>
<Attribute>unknown</Attribute>
<CType>int</CType>
</RtlPorts>
<RtlPorts>
<name>m_axi_gmem_AWUSER</name>
<Object>gmem</Object>
<Type>pointer</Type>
<Scope></Scope>
<IOProtocol>m_axi</IOProtocol>
<IOConfig></IOConfig>
<Dir>out</Dir>
<Bits>1</Bits>
<Attribute>unknown</Attribute>
<CType>int</CType>
</RtlPorts>
<RtlPorts>
<name>m_axi_gmem_WVALID</name>
<Object>gmem</Object>
<Type>pointer</Type>
<Scope></Scope>
<IOProtocol>m_axi</IOProtocol>
<IOConfig></IOConfig>
<Dir>out</Dir>
<Bits>1</Bits>
<Attribute>unknown</Attribute>
<CType>int</CType>
</RtlPorts>
<RtlPorts>
<name>m_axi_gmem_WREADY</name>
<Object>gmem</Object>
<Type>pointer</Type>
<Scope></Scope>
<IOProtocol>m_axi</IOProtocol>
<IOConfig></IOConfig>
<Dir>in</Dir>
<Bits>1</Bits>
<Attribute>unknown</Attribute>
<CType>int</CType>
</RtlPorts>
<RtlPorts>
<name>m_axi_gmem_WDATA</name>
<Object>gmem</Object>
<Type>pointer</Type>
<Scope></Scope>
<IOProtocol>m_axi</IOProtocol>
<IOConfig></IOConfig>
<Dir>out</Dir>
<Bits>32</Bits>
<Attribute>unknown</Attribute>
<CType>int</CType>
</RtlPorts>
<RtlPorts>
<name>m_axi_gmem_WSTRB</name>
<Object>gmem</Object>
<Type>pointer</Type>
<Scope></Scope>
<IOProtocol>m_axi</IOProtocol>
<IOConfig></IOConfig>
<Dir>out</Dir>
<Bits>4</Bits>
<Attribute>unknown</Attribute>
<CType>int</CType>
</RtlPorts>
<RtlPorts>
<name>m_axi_gmem_WLAST</name>
<Object>gmem</Object>
<Type>pointer</Type>
<Scope></Scope>
<IOProtocol>m_axi</IOProtocol>
<IOConfig></IOConfig>
<Dir>out</Dir>
<Bits>1</Bits>
<Attribute>unknown</Attribute>
<CType>int</CType>
</RtlPorts>
<RtlPorts>
<name>m_axi_gmem_WID</name>
<Object>gmem</Object>
<Type>pointer</Type>
<Scope></Scope>
<IOProtocol>m_axi</IOProtocol>
<IOConfig></IOConfig>
<Dir>out</Dir>
<Bits>1</Bits>
<Attribute>unknown</Attribute>
<CType>int</CType>
</RtlPorts>
<RtlPorts>
<name>m_axi_gmem_WUSER</name>
<Object>gmem</Object>
<Type>pointer</Type>
<Scope></Scope>
<IOProtocol>m_axi</IOProtocol>
<IOConfig></IOConfig>
<Dir>out</Dir>
<Bits>1</Bits>
<Attribute>unknown</Attribute>
<CType>int</CType>
</RtlPorts>
<RtlPorts>
<name>m_axi_gmem_ARVALID</name>
<Object>gmem</Object>
<Type>pointer</Type>
<Scope></Scope>
<IOProtocol>m_axi</IOProtocol>
<IOConfig></IOConfig>
<Dir>out</Dir>
<Bits>1</Bits>
<Attribute>unknown</Attribute>
<CType>int</CType>
</RtlPorts>
<RtlPorts>
<name>m_axi_gmem_ARREADY</name>
<Object>gmem</Object>
<Type>pointer</Type>
<Scope></Scope>
<IOProtocol>m_axi</IOProtocol>
<IOConfig></IOConfig>
<Dir>in</Dir>
<Bits>1</Bits>
<Attribute>unknown</Attribute>
<CType>int</CType>
</RtlPorts>
<RtlPorts>
<name>m_axi_gmem_ARADDR</name>
<Object>gmem</Object>
<Type>pointer</Type>
<Scope></Scope>
<IOProtocol>m_axi</IOProtocol>
<IOConfig></IOConfig>
<Dir>out</Dir>
<Bits>64</Bits>
<Attribute>unknown</Attribute>
<CType>int</CType>
</RtlPorts>
<RtlPorts>
<name>m_axi_gmem_ARID</name>
<Object>gmem</Object>
<Type>pointer</Type>
<Scope></Scope>
<IOProtocol>m_axi</IOProtocol>
<IOConfig></IOConfig>
<Dir>out</Dir>
<Bits>1</Bits>
<Attribute>unknown</Attribute>
<CType>int</CType>
</RtlPorts>
<RtlPorts>
<name>m_axi_gmem_ARLEN</name>
<Object>gmem</Object>
<Type>pointer</Type>
<Scope></Scope>
<IOProtocol>m_axi</IOProtocol>
<IOConfig></IOConfig>
<Dir>out</Dir>
<Bits>8</Bits>
<Attribute>unknown</Attribute>
<CType>int</CType>
</RtlPorts>
<RtlPorts>
<name>m_axi_gmem_ARSIZE</name>
<Object>gmem</Object>
<Type>pointer</Type>
<Scope></Scope>
<IOProtocol>m_axi</IOProtocol>
<IOConfig></IOConfig>
<Dir>out</Dir>
<Bits>3</Bits>
<Attribute>unknown</Attribute>
<CType>int</CType>
</RtlPorts>
<RtlPorts>
<name>m_axi_gmem_ARBURST</name>
<Object>gmem</Object>
<Type>pointer</Type>
<Scope></Scope>
<IOProtocol>m_axi</IOProtocol>
<IOConfig></IOConfig>
<Dir>out</Dir>
<Bits>2</Bits>
<Attribute>unknown</Attribute>
<CType>int</CType>
</RtlPorts>
<RtlPorts>
<name>m_axi_gmem_ARLOCK</name>
<Object>gmem</Object>
<Type>pointer</Type>
<Scope></Scope>
<IOProtocol>m_axi</IOProtocol>
<IOConfig></IOConfig>
<Dir>out</Dir>
<Bits>2</Bits>
<Attribute>unknown</Attribute>
<CType>int</CType>
</RtlPorts>
<RtlPorts>
<name>m_axi_gmem_ARCACHE</name>
<Object>gmem</Object>
<Type>pointer</Type>
<Scope></Scope>
<IOProtocol>m_axi</IOProtocol>
<IOConfig></IOConfig>
<Dir>out</Dir>
<Bits>4</Bits>
<Attribute>unknown</Attribute>
<CType>int</CType>
</RtlPorts>
<RtlPorts>
<name>m_axi_gmem_ARPROT</name>
<Object>gmem</Object>
<Type>pointer</Type>
<Scope></Scope>
<IOProtocol>m_axi</IOProtocol>
<IOConfig></IOConfig>
<Dir>out</Dir>
<Bits>3</Bits>
<Attribute>unknown</Attribute>
<CType>int</CType>
</RtlPorts>
<RtlPorts>
<name>m_axi_gmem_ARQOS</name>
<Object>gmem</Object>
<Type>pointer</Type>
<Scope></Scope>
<IOProtocol>m_axi</IOProtocol>
<IOConfig></IOConfig>
<Dir>out</Dir>
<Bits>4</Bits>
<Attribute>unknown</Attribute>
<CType>int</CType>
</RtlPorts>
<RtlPorts>
<name>m_axi_gmem_ARREGION</name>
<Object>gmem</Object>
<Type>pointer</Type>
<Scope></Scope>
<IOProtocol>m_axi</IOProtocol>
<IOConfig></IOConfig>
<Dir>out</Dir>
<Bits>4</Bits>
<Attribute>unknown</Attribute>
<CType>int</CType>
</RtlPorts>
<RtlPorts>
<name>m_axi_gmem_ARUSER</name>
<Object>gmem</Object>
<Type>pointer</Type>
<Scope></Scope>
<IOProtocol>m_axi</IOProtocol>
<IOConfig></IOConfig>
<Dir>out</Dir>
<Bits>1</Bits>
<Attribute>unknown</Attribute>
<CType>int</CType>
</RtlPorts>
<RtlPorts>
<name>m_axi_gmem_RVALID</name>
<Object>gmem</Object>
<Type>pointer</Type>
<Scope></Scope>
<IOProtocol>m_axi</IOProtocol>
<IOConfig></IOConfig>
<Dir>in</Dir>
<Bits>1</Bits>
<Attribute>unknown</Attribute>
<CType>int</CType>
</RtlPorts>
<RtlPorts>
<name>m_axi_gmem_RREADY</name>
<Object>gmem</Object>
<Type>pointer</Type>
<Scope></Scope>
<IOProtocol>m_axi</IOProtocol>
<IOConfig></IOConfig>
<Dir>out</Dir>
<Bits>1</Bits>
<Attribute>unknown</Attribute>
<CType>int</CType>
</RtlPorts>
<RtlPorts>
<name>m_axi_gmem_RDATA</name>
<Object>gmem</Object>
<Type>pointer</Type>
<Scope></Scope>
<IOProtocol>m_axi</IOProtocol>
<IOConfig></IOConfig>
<Dir>in</Dir>
<Bits>32</Bits>
<Attribute>unknown</Attribute>
<CType>int</CType>
</RtlPorts>
<RtlPorts>
<name>m_axi_gmem_RLAST</name>
<Object>gmem</Object>
<Type>pointer</Type>
<Scope></Scope>
<IOProtocol>m_axi</IOProtocol>
<IOConfig></IOConfig>
<Dir>in</Dir>
<Bits>1</Bits>
<Attribute>unknown</Attribute>
<CType>int</CType>
</RtlPorts>
<RtlPorts>
<name>m_axi_gmem_RID</name>
<Object>gmem</Object>
<Type>pointer</Type>
<Scope></Scope>
<IOProtocol>m_axi</IOProtocol>
<IOConfig></IOConfig>
<Dir>in</Dir>
<Bits>1</Bits>
<Attribute>unknown</Attribute>
<CType>int</CType>
</RtlPorts>
<RtlPorts>
<name>m_axi_gmem_RUSER</name>
<Object>gmem</Object>
<Type>pointer</Type>
<Scope></Scope>
<IOProtocol>m_axi</IOProtocol>
<IOConfig></IOConfig>
<Dir>in</Dir>
<Bits>1</Bits>
<Attribute>unknown</Attribute>
<CType>int</CType>
</RtlPorts>
<RtlPorts>
<name>m_axi_gmem_RRESP</name>
<Object>gmem</Object>
<Type>pointer</Type>
<Scope></Scope>
<IOProtocol>m_axi</IOProtocol>
<IOConfig></IOConfig>
<Dir>in</Dir>
<Bits>2</Bits>
<Attribute>unknown</Attribute>
<CType>int</CType>
</RtlPorts>
<RtlPorts>
<name>m_axi_gmem_BVALID</name>
<Object>gmem</Object>
<Type>pointer</Type>
<Scope></Scope>
<IOProtocol>m_axi</IOProtocol>
<IOConfig></IOConfig>
<Dir>in</Dir>
<Bits>1</Bits>
<Attribute>unknown</Attribute>
<CType>int</CType>
</RtlPorts>
<RtlPorts>
<name>m_axi_gmem_BREADY</name>
<Object>gmem</Object>
<Type>pointer</Type>
<Scope></Scope>
<IOProtocol>m_axi</IOProtocol>
<IOConfig></IOConfig>
<Dir>out</Dir>
<Bits>1</Bits>
<Attribute>unknown</Attribute>
<CType>int</CType>
</RtlPorts>
<RtlPorts>
<name>m_axi_gmem_BRESP</name>
<Object>gmem</Object>
<Type>pointer</Type>
<Scope></Scope>
<IOProtocol>m_axi</IOProtocol>
<IOConfig></IOConfig>
<Dir>in</Dir>
<Bits>2</Bits>
<Attribute>unknown</Attribute>
<CType>int</CType>
</RtlPorts>
<RtlPorts>
<name>m_axi_gmem_BID</name>
<Object>gmem</Object>
<Type>pointer</Type>
<Scope></Scope>
<IOProtocol>m_axi</IOProtocol>
<IOConfig></IOConfig>
<Dir>in</Dir>
<Bits>1</Bits>
<Attribute>unknown</Attribute>
<CType>int</CType>
</RtlPorts>
<RtlPorts>
<name>m_axi_gmem_BUSER</name>
<Object>gmem</Object>
<Type>pointer</Type>
<Scope></Scope>
<IOProtocol>m_axi</IOProtocol>
<IOConfig></IOConfig>
<Dir>in</Dir>
<Bits>1</Bits>
<Attribute>unknown</Attribute>
<CType>int</CType>
</RtlPorts>
</InterfaceSummary>

</profile>
